{"list":[{"avatar":"http:\/\/static.tongyigg.com\/images\/a2d171c4daf440ee9b5f6a9edd43259d.jpg","nickname":"\u4f60\u7684\u6c85\u6c85\u54e6","uid":23128915,"liveid":11838133,"watches":228},{"avatar":"http:\/\/static.tongyigg.com\/images\/4ebb0a8fd38fed95770f06888c2cc2b6.jpg","nickname":"\u5c0f\u4e03\u2764\ufe0f","uid":23348479,"liveid":11837652,"watches":134357},{"avatar":"http:\/\/static.tongyigg.com\/images\/16d221739feea9b340f715c111cb8ace.jpg","nickname":"Aimini\u5e42","uid":24250881,"liveid":11838140,"watches":2540},{"avatar":"http:\/\/static.tongyigg.com\/images\/ab3479c7e9dbb8701a48fab596bf79ea.jpg","nickname":"\u543e\u4e3b\u3001\u8336\u8336\u3002","uid":24242808,"liveid":11838098,"watches":6763},{"avatar":"http:\/\/static.tongyigg.com\/images\/e3b847e7ff0855662c6239265fdcd588.jpg","nickname":"\u5c0f\u60c5\u7eea\u2026\u2026","uid":20637047,"liveid":11838138,"watches":3696},{"avatar":"http:\/\/static.tongyigg.com\/images\/67fc7cc37545ef9819ed542ed4bedbd6.jpg","nickname":"\u5c0f\u96c5\ud83d\udcab\ufe0f","uid":23848817,"liveid":11837885,"watches":73379},{"avatar":"http:\/\/static.tongyigg.com\/images\/74cf49f6fc11a3c207fa468824f612f9.jpg","nickname":"\u7b11\u7b11\u3002\u3002\u3002","uid":26334804,"liveid":11838120,"watches":6066},{"avatar":"http:\/\/static.tongyigg.com\/images\/1e4ba640b66fa85eee3982ad701aa110.jpg","nickname":"7 \ud83d\udc49 \u5c0f\u963f\u6597","uid":24044386,"liveid":11838080,"watches":7577},{"avatar":"http:\/\/static.tongyigg.com\/images\/711af000a4c129fe8249883bf327a064.jpg","nickname":"kiss\u3001\u96ea","uid":23518578,"liveid":11837982,"watches":19571},{"avatar":"http:\/\/static.tongyigg.com\/images\/7d629dbb304a58cd5a04223b8fbc0e51.jpg","nickname":"\u5c0f\u534a\u4ed9\ud83d\udc83","uid":23545740,"liveid":11838131,"watches":2775},{"avatar":"http:\/\/static.tongyigg.com\/images\/f7986a71e125be59c4cbf9af43817c2f.jpg","nickname":"7\ud83d\udcab\u7cd6\u5566\u5566","uid":23685100,"liveid":11838005,"watches":22662},{"avatar":"http:\/\/static.tongyigg.com\/images\/7a6fa38d595eba787869a4e288b254f7.jpg","nickname":"\u8089\u8089\ud83d\udc7c\u7b28\u7b28","uid":26174883,"liveid":11837958,"watches":16024},{"avatar":"http:\/\/static.tongyigg.com\/images\/09f2724f743a3d6af2c2b9191ae891f4.jpg","nickname":"\ud83c\udf08 \u8dc3\u8dc3\u5440","uid":25297069,"liveid":11837949,"watches":33046},{"avatar":"http:\/\/static.tongyigg.com\/images\/f089405344c873c27475373fd8df676c.jpg","nickname":"\ud83d\udc83\u5ba0\u5e78\u821e\u738b\ud83d\udc83","uid":23660440,"liveid":11838108,"watches":1597},{"avatar":"http:\/\/static.tongyigg.com\/images\/f133cccb7be77d7729462873cc503894.jpg","nickname":"Mrs\u767d\u9732.","uid":26198802,"liveid":11838123,"watches":2521},{"avatar":"http:\/\/static.tongyigg.com\/images\/dc2dddfccd52428f043758702022ae44.jpg","nickname":"\u4f60\u53ef\u7231\u7684\u4f73\u7426\ud83d\udc95","uid":26572984,"liveid":11837723,"watches":34232},{"avatar":"http:\/\/static.tongyigg.com\/images\/75b69c5fa782552b419dda790ded20c9.jpg","nickname":"\u68a6\u5bb6-\u5c0f\u5d3d\u5416","uid":26991671,"liveid":11837868,"watches":14922},{"avatar":"http:\/\/static.tongyigg.com\/images\/643e81ad3ce549d35b78f8702d558f4f.jpg","nickname":"\u6797\u4e5f\u4e5f","uid":23017860,"liveid":11838031,"watches":9278},{"avatar":"http:\/\/static.tongyigg.com\/images\/63fe829b14be582eca2a2766f9989ed7.jpg","nickname":"\u7476\u7476\u5b64\u5355\u6c42\u966a\u4f34","uid":26826620,"liveid":11838143,"watches":2012},{"avatar":"http:\/\/static.tongyigg.com\/images\/40a2d72776f6fb3175a9b83c6dd846c9.jpg","nickname":"H\u3001\ud83c\udf38\u6797CC\u554a","uid":23667255,"liveid":11838129,"watches":2779}],"msg":"\u64cd\u4f5c\u6210\u529f"}